[
  {
    "description": "这是一个会返回cookies信息的get请求",
    "request":
    {

      "uri": "/getCookies",
      "method": "get"
    },
    "response":
    {
      "headers":
      {
        "Content-Type": "text/html;charset=gbk"
      },
      "cookies":
      {
        "login": "true"
      },
      "text": "恭喜你获得cookies信息成功"
    }

  },



  {
    "description": "这是一个带cookies信息的get请求",
    "request":
    {
      "uri": "/getwithCookies",
      "method": "get",
      "cookies":
      {
        "login": "true"
      }
    },


    "response":
    {
      "headers":
      {
        "Content-Type": "text/html;charset=gbk"
      },
      "text": "这是带cookies信息的响应"
    }
  },

  {
    "description":"这是一个带cookies的post请求",
    "request":
    {
      "uri": "/cookieswithCookies",
      "method": "post",
      "cookies":
      {
        "login": "true"
      },
      "json":
      {
        "name": "zhangsan",
        "age": "18"
      }
    },
    "response":
    {
      "status": 200,
      "json":
      {
        "zhangsan": "success",
        "status": "1"
      }
    }

  }

]